Workbook

Sheet README
A1: Diagram Automation — CSV Data Specification
A3: Purpose | B3: Define one universal, tool-agnostic data format (CSV/Excel) from which a custom renderer can generate diagrams automatically. One schema covers EA/ArchiMate models, flowcharts & swimlanes, org charts, network/deployment diagrams, and ERDs.
A5: Pipeline | B5: 1) Author data in Nodes + Edges sheets (or CSVs) → 2) Renderer resolves entity_type via Shape_Library and relation_type via Line_Rules → 3) Sizing engine computes W×H per node (Sizing_Layout rules) → 4) Layout engine picks algorithm from Scenario_Catalog → 5) Output SVG / draw.io XML / PNG.
A7: Sheet guide
A8: Scenario_Catalog | B8: Every diagram scenario identified, with the layout algorithm and key challenge for each.
A9: Shape_Library | B9: Entity type → shape, default size, colors. This solves "which shape to use".
A10: Line_Rules | B10: Relationship type → line style, arrowheads, routing. This solves "which line to use".
A11: Sizing_Layout | B11: Auto-sizing formulas and spacing constants. This solves the sizing/shaping challenge.
A12: Diagrams | B12: Registry of sample diagrams (one row = one output file).
A13: Nodes | B13: Sample node data for 5 demo diagrams. computed_w/computed_h are LIVE Excel formulas implementing the sizing rules.
A14: Edges | B14: Sample edge data for the same demo diagrams.
A16: Design principles | B16: Separation of data (Nodes/Edges) from presentation (rule sheets): business users only fill 6–8 columns; the renderer owns geometry. Nesting via parent_id gives containers (layers, swimlanes, zones) for free. Overrides (w_override, fill_override) allow exceptions without breaking automation.

Sheet Scenario_Catalog
A1: scenario_id | B1: family | C1: scenario_name | D1: description / when used | E1: typical_entities | F1: typical_relations | G1: layout_algorithm | H1: containers? | I1: key_challenge
A2: EA-01 | B2: EA | C2: ArchiMate layered view | D2: Business / Application / Technology stack view of an enterprise; the classic EA deliverable. | E2: business_process, application_component, node, services | F2: serving, realization, assignment | G2: Horizontal layer bands; grid placement inside each band | H2: Yes (layer bands) | I2: Keeping cross-layer edges vertical and readable
A3: EA-02 | B3: EA | C3: Capability map | D3: Nested business capabilities L1→L3 shown as tiles inside tiles. | E3: capability | F3: composition (implicit via nesting) | G3: Nested grid (treemap-like), fixed columns per level | H3: Yes (nested) | I3: Auto-sizing parents to fit children exactly
A4: EA-03 | B4: EA | C4: Application landscape | D4: All applications grouped by domain, colored by lifecycle status. | E4: application_component, group | F4: flow (data exchanges) optional | G4: Grouped grid; groups ordered by domain | H4: Yes (domain groups) | I4: Conditional color coding from data attributes
A5: EA-04 | B5: EA | C5: Metamodel / concept map | D5: Concepts and their allowed relationships (like the EAF metamodel on screen). | E5: all ArchiMate types | F5: all relation types + labels | G5: Orthogonal / force-directed with layer background zones | H5: Optional | I5: Many edge crossings; needs orthogonal routing + label placement
A6: FL-01 | B6: Flowchart | C6: Basic flowchart | D6: Step-by-step process with decisions and terminators. | E6: start_end, process, decision, data_io, document | F6: sequence_flow (with yes/no labels) | G6: Sugiyama layered, top-to-bottom; decision branches left/right | H6: No | I6: Branch/merge symmetry; diamond aspect ratio vs label length
A7: FL-02 | B7: Flowchart | C7: Swimlane / cross-functional | D7: Process steps assigned to roles or departments in lanes. | E7: lane + flowchart shapes | F7: sequence_flow, message_flow | G7: Ranked flow constrained to lane columns/rows | H7: Yes (lanes) | I7: Lane height driven by busiest lane; edges crossing lanes
A8: FL-03 | B8: Flowchart | C8: Decision tree | D8: Branching logic, each path ends in an outcome. | E8: decision, process, start_end | F8: sequence_flow (labelled) | G8: Tree layout, top-down, balanced subtrees | H8: No | I8: Width explosion at deep levels; needs subtree compaction
A9: OR-01 | B9: OrgChart | C9: Org chart / hierarchy | D9: Reporting structure from CSV HR export. | E9: person_card, department | F9: reports_to | G9: Tree layout, top-down; siblings ordered by data | H9: Optional (departments) | I9: Very wide trees → stagger/compress leaf rows
A10: OR-02 | B10: OrgChart | C10: Matrix org / dotted-line | D10: Hierarchy plus secondary (functional) reporting lines. | E10: person_card | F10: reports_to, dotted_reporting | G10: Tree for primary edges; secondary edges routed around | H10: Optional | I10: Secondary edges must not be confused with primary
A11: NW-01 | B11: Network | C11: Network topology | D11: Zones (Internet/DMZ/Internal) with devices and links. | E11: cloud, firewall, router, switch, load_balancer, server, zone | F11: physical_link, logical_link, vpn_tunnel | G11: Tiered top-down by zone; devices grid inside zone | H11: Yes (zones) | I11: Redundant links (N×M) need parallel edge offsets
A12: NW-02 | B12: Network | C12: Deployment diagram | D12: What runs where: artifacts inside runtimes inside servers. | E12: node, device, artifact, execution_env | F12: deployed_on (nesting), communicates | G12: Nested containers + orthogonal links | H12: Yes (3+ levels deep) | I12: Deep nesting: size must propagate bottom-up
... A14: ER-02 | B14: ERD | C14: Data lineage / flow | D14: How data moves between systems, left to right. | E14: application_component, data_object, database | F14: data_flow (labelled) | G14: Layered left-to-right (rank = pipeline stage) | H14: Optional (stages) | I14: Long horizontal edges need waypoint hints

Sheet Sizing_Layout
A1: rule_id | B1: category | C1: rule | D1: value / formula | E1: applies_to
A2: SZ-01 | B2: Text metrics | C2: Average character width (Arial 12px) used for width estimation | D2: CHAR_W = 7 px | LINE_H = 16 px | E2: all auto_size shapes
A3: SZ-02 | B3: Node width | C3: Width grows with label, bounded | D3: w = CLAMP(min_w, LEN(label)×CHAR_W + 2×PAD_X, max_w=260) | E3: auto_size = Y
A4: SZ-03 | B4: Node height | C4: Height grows when label wraps | D4: lines = CEIL(LEN(label)×CHAR_W ÷ (w − 2×PAD_X)); h = MAX(min_h, lines×LINE_H + 2×PAD_Y) | E4: auto_size = Y
A5: SZ-04 | B5: Padding | C5: Inner text padding | D5: PAD_X = 12 px, PAD_Y = 10 px (icons: +18 px right) | E5: all shapes
A6: SZ-05 | B6: Grid snap | C6: All x, y, w, h snap to grid | D6: GRID = 10 px | E6: layout engine
A7: SZ-06 | B7: Diamond ratio | C7: Decision diamonds keep aspect ratio; label wraps to fit | D7: w : h = 1.75 : 1; if label > 20 chars → wrap, grow both axes | E7: decision
A8: SZ-07 | B8: Row-list shapes | C8: ERD entities sized by attribute count | D8: h = TITLE_H(30) + rows×ROW_H(22); w = MAX(widest row text + 40, 160) | E8: entity, view
A9: SZ-08 | B9: Container fit | C9: Parents auto-grow bottom-up to wrap children | D9: w/h = child bbox + PAD_C(20) each side + HEADER_H(28) top; computed leaf-first | E9: all containers
A10: SZ-09 | B10: Lane sizing | C10: All lanes share length; thickness set by busiest lane | D10: lane_len = max over lanes; lane_thickness = max node span + 2×PAD_C | E10: lane
A11: SZ-10 | B11: Sibling spacing | C11: Horizontal gap between nodes at same rank | D11: GAP_X = 40 px (org charts: 24 px) | E11: tree/layered layouts
A12: SZ-11 | B12: Rank spacing | C12: Vertical gap between ranks/levels | D12: GAP_Y = 60 px (flowcharts: 50 px) | E12: tree/layered layouts
... A17: SZ-16 | B17: Font scale | C17: Font sizes by role | D17: node label 12 px; container title 13 px bold; edge label 10 px | E17: renderer

Sheet Diagrams
A1: diagram_id | B1: scenario_id | C1: title | D1: direction | E1: theme | F1: notes
A2: D1 | B2: EA-01 | C2: Retail Platform — Layered View | D2: layers top-down | E2: archimate | F2: Business → Application → Technology
A3: D2 | B3: FL-01 | C3: Order Approval Process | D3: top-down | E3: classic | F3: One decision, reject loop
A4: D3 | B4: OR-01 | C4: Engineering Org | D4: top-down | E4: corporate | F4: From HR CSV export
A5: D4 | B5: NW-01 | C5: Web Platform Topology | D5: tiers top-down | E5: network | F5: Internet → DMZ → Internal
A6: D5 | B6: ER-01 | C6: Order Management Schema | D6: orthogonal grid | E6: erd | F6: Crow's foot

Sheet Nodes
A1: diagram_id | B1: node_id | C1: parent_id | D1: entity_type | E1: label | F1: rank_hint | G1: order_hint | H1: w_override | I1: h_override | J1: computed_w | K1: computed_h | L1: fill_override | M1: metadata
A2: D1 | B2: L1 | D2: group | E2: Business Layer | F2: 1 | G2: 1 | J2: =IF(H2<>"",H2,MIN(260,MAX(VLOOKUP(D2,Shape_Library!$A:$H,7,0),LEN(E2)*7+24))) | K2: =IF(I2<>"",I2,MAX(VLOOKUP(D2,Shape_Library!$A:$H,8,0),CEILING(LEN(E2)*7/(J2-24),1)*16+20)) | L2: #FFFDE7 | M2: layer=business
A3: D1 | B3: L2 | D3: group | E3: Application Layer | F3: 2 | G3: 1 | J3: =IF(H3<>"",H3,MIN(260,MAX(VLOOKUP(D3,Shape_Library!$A:$H,7,0),LEN(E3)*7+24))) | K3: =IF(I3<>"",I3,MAX(VLOOKUP(D3,Shape_Library!$A:$H,8,0),CEILING(LEN(E3)*7/(J3-24),1)*16+20)) | L3: #E8F4FB | M3: layer=application
A4: D1 | B4: L3 | D4: group | E4: Technology Layer | F4: 3 | G4: 1 | J4: =IF(H4<>"",H4,MIN(260,MAX(VLOOKUP(D4,Shape_Library!$A:$H,7,0),LEN(E4)*7+24))) | K4: =IF(I4<>"",I4,MAX(VLOOKUP(D4,Shape_Library!$A:$H,8,0),CEILING(LEN(E4)*7/(J4-24),1)*16+20)) | L4: #EDF7ED | M4: layer=technology
A5: D1 | B5: B1 | C5: L1 | D5: business_process | E5: Order Fulfilment | F5: 1 | G5: 1 | J5: =IF(H5<>"",H5,MIN(260,MAX(VLOOKUP(D5,Shape_Library!$A:$H,7,0),LEN(E5)*7+24))) | K5: =IF(I5<>"",I5,MAX(VLOOKUP(D5,Shape_Library!$A:$H,8,0),CEILING(LEN(E5)*7/(J5-24),1)*16+20))
A6: D1 | B6: B2 | C6: L1 | D6: business_service | E6: Customer Support Service | F6: 1 | G6: 2 | J6: =IF(H6<>"",H6,MIN(260,MAX(VLOOKUP(D6,Shape_Library!$A:$H,7,0),LEN(E6)*7+24))) | K6: =IF(I6<>"",I6,MAX(VLOOKUP(D6,Shape_Library!$A:$H,8,0),CEILING(LEN(E6)*7/(J6-24),1)*16+20))
A7: D1 | B7: A1 | C7: L2 | D7: application_component | E7: E-Commerce Platform | F7: 1 | G7: 1 | J7: =IF(H7<>"",H7,MIN(260,MAX(VLOOKUP(D7,Shape_Library!$A:$H,7,0),LEN(E7)*7+24))) | K7: =IF(I7<>"",I7,MAX(VLOOKUP(D7,Shape_Library!$A:$H,8,0),CEILING(LEN(E7)*7/(J7-24),1)*16+20)) | M7: lifecycle=active
A8: D1 | B8: A2 | C8: L2 | D8: application_component | E8: CRM System | F8: 1 | G8: 2 | J8: =IF(H8<>"",H8,MIN(260,MAX(VLOOKUP(D8,Shape_Library!$A:$H,7,0),LEN(E8)*7+24))) | K8: =IF(I8<>"",I8,MAX(VLOOKUP(D8,Shape_Library!$A:$H,8,0),CEILING(LEN(E8)*7/(J8-24),1)*16+20)) | M8: lifecycle=phase-out
A9: D1 | B9: A3 | C9: L2 | D9: application_service | E9: Order Management Service | F9: 1 | G9: 3 | J9: =IF(H9<>"",H9,MIN(260,MAX(VLOOKUP(D9,Shape_Library!$A:$H,7,0),LEN(E9)*7+24))) | K9: =IF(I9<>"",I9,MAX(VLOOKUP(D9,Shape_Library!$A:$H,8,0),CEILING(LEN(E9)*7/(J9-24),1)*16+20))
A10: D1 | B10: T1 | C10: L3 | D10: node | E10: Kubernetes Cluster | F10: 1 | G10: 1 | J10: =IF(H10<>"",H10,MIN(260,MAX(VLOOKUP(D10,Shape_Library!$A:$H,7,0),LEN(E10)*7+24))) | K10: =IF(I10<>"",I10,MAX(VLOOKUP(D10,Shape_Library!$A:$H,8,0),CEILING(LEN(E10)*7/(J10-24),1)*16+20))
A11: D1 | B11: T2 | C11: L3 | D11: device | E11: Database Server | F11: 1 | G11: 2 | J11: =IF(H11<>"",H11,MIN(260,MAX(VLOOKUP(D11,Shape_Library!$A:$H,7,0),LEN(E11)*7+24))) | K11: =IF(I11<>"",I11,MAX(VLOOKUP(D11,Shape_Library!$A:$H,8,0),CEILING(LEN(E11)*7/(J11-24),1)*16+20))
A12: D2 | B12: F1 | D12: start_end | E12: Start | F12: 1 | G12: 1 | J12: =IF(H12<>"",H12,MIN(260,MAX(VLOOKUP(D12,Shape_Library!$A:$H,7,0),LEN(E12)*7+24))) | K12: =IF(I12<>"",I12,MAX(VLOOKUP(D12,Shape_Library!$A:$H,8,0),CEILING(LEN(E12)*7/(J12-24),1)*16+20))
A13: D2 | B13: F2 | D13: process | E13: Receive Purchase Order | F13: 2 | G13: 1 | J13: =IF(H13<>"",H13,MIN(260,MAX(VLOOKUP(D13,Shape_Library!$A:$H,7,0),LEN(E13)*7+24))) | K13: =IF(I13<>"",I13,MAX(VLOOKUP(D13,Shape_Library!$A:$H,8,0),CEILING(LEN(E13)*7/(J13-24),1)*16+20))
A14: D2 | B14: F3 | D14: decision | E14: Budget Approved? | F14: 3 | G14: 1 | J14: =IF(H14<>"",H14,MIN(260,MAX(VLOOKUP(D14,Shape_Library!$A:$H,7,0),LEN(E14)*7+24))) | K14: =IF(I14<>"",I14,MAX(VLOOKUP(D14,Shape_Library!$A:$H,8,0),CEILING(LEN(E14)*7/(J14-24),1)*16+20))
A15: D2 | B15: F4 | D15: process | E15: Process Payment | F15: 4 | G15: 1 | J15: =IF(H15<>"",H15,MIN(260,MAX(VLOOKUP(D15,Shape_Library!$A:$H,7,0),LEN(E15)*7+24))) | K15: =IF(I15<>"",I15,MAX(VLOOKUP(D15,Shape_Library!$A:$H,8,0),CEILING(LEN(E15)*7/(J15-24),1)*16+20))
A16: D2 | B16: F5 | D16: process | E16: Notify Requester of Rejection | F16: 4 | G16: 2 | J16: =IF(H16<>"",H16,MIN(260,MAX(VLOOKUP(D16,Shape_Library!$A:$H,7,0),LEN(E16)*7+24))) | K16: =IF(I16<>"",I16,MAX(VLOOKUP(D16,Shape_Library!$A:$H,8,0),CEILING(LEN(E16)*7/(J16-24),1)*16+20))
A17: D2 | B17: F6 | D17: data_io | E17: Update ERP Record | F17: 5 | G17: 1 | J17: =IF(H17<>"",H17,MIN(260,MAX(VLOOKUP(D17,Shape_Library!$A:$H,7,0),LEN(E17)*7+24))) | K17: =IF(I17<>"",I17,MAX(VLOOKUP(D17,Shape_Library!$A:$H,8,0),CEILING(LEN(E17)*7/(J17-24),1)*16+20))
A18: D2 | B18: F7 | D18: start_end | E18: End | F18: 6 | G18: 1 | J18: =IF(H18<>"",H18,MIN(260,MAX(VLOOKUP(D18,Shape_Library!$A:$H,7,0),LEN(E18)*7+24))) | K18: =IF(I18<>"",I18,MAX(VLOOKUP(D18,Shape_Library!$A:$H,8,0),CEILING(LEN(E18)*7/(J18-24),1)*16+20))
A19: D3 | B19: P1 | D19: person_card | E19: Priya Sharma — VP Engineering | F19: 1 | G19: 1 | J19: =IF(H19<>"",H19,MIN(260,MAX(VLOOKUP(D19,Shape_Library!$A:$H,7,0),LEN(E19)*7+24))) | K19: =IF(I19<>"",I19,MAX(VLOOKUP(D19,Shape_Library!$A:$H,8,0),CEILING(LEN(E19)*7/(J19-24),1)*16+20)) | M19: dept=Engineering
A20: D3 | B20: P2 | D20: person_card | E20: Jacob Cherian — Director, Platform | F20: 2 | G20: 1 | J20: =IF(H20<>"",H20,MIN(260,MAX(VLOOKUP(D20,Shape_Library!$A:$H,7,0),LEN(E20)*7+24))) | K20: =IF(I20<>"",I20,MAX(VLOOKUP(D20,Shape_Library!$A:$H,8,0),CEILING(LEN(E20)*7/(J20-24),1)*16+20))
A21: D3 | B21: P3 | D21: person_card | E21: Abhijit Davande — Director, Apps | F21: 2 | G21: 2 | J21: =IF(H21<>"",H21,MIN(260,MAX(VLOOKUP(D21,Shape_Library!$A:$H,7,0),LEN(E21)*7+24))) | K21: =IF(I21<>"",I21,MAX(VLOOKUP(D21,Shape_Library!$A:$H,8,0),CEILING(LEN(E21)*7/(J21-24),1)*16+20))
A22: D3 | B22: P4 | D22: person_card | E22: Manav Rathi — Senior Engineer | F22: 3 | G22: 1 | J22: =IF(H22<>"",H22,MIN(260,MAX(VLOOKUP(D22,Shape_Library!$A:$H,7,0),LEN(E22)*7+24))) | K22: =IF(I22<>"",I22,MAX(VLOOKUP(D22,Shape_Library!$A:$H,8,0),CEILING(LEN(E22)*7/(J22-24),1)*16+20))
A23: D3 | B23: P5 | D23: person_card | E23: Palaash Padman — Engineer | F23: 3 | G23: 2 | J23: =IF(H23<>"",H23,MIN(260,MAX(VLOOKUP(D23,Shape_Library!$A:$H,7,0),LEN(E23)*7+24))) | K23: =IF(I23<>"",I23,MAX(VLOOKUP(D23,Shape_Library!$A:$H,8,0),CEILING(LEN(E23)*7/(J23-24),1)*16+20))
A24: D4 | B24: N0 | D24: cloud | E24: Internet | F24: 1 | G24: 1 | J24: =IF(H24<>"",H24,MIN(260,MAX(VLOOKUP(D24,Shape_Library!$A:$H,7,0),LEN(E24)*7+24))) | K24: =IF(I24<>"",I24,MAX(VLOOKUP(D24,Shape_Library!$A:$H,8,0),CEILING(LEN(E24)*7/(J24-24),1)*16+20))
A25: D4 | B25: Z1 | D25: zone | E25: DMZ | F25: 2 | G25: 1 | J25: =IF(H25<>"",H25,MIN(260,MAX(VLOOKUP(D25,Shape_Library!$A:$H,7,0),LEN(E25)*7+24))) | K25: =IF(I25<>"",I25,MAX(VLOOKUP(D25,Shape_Library!$A:$H,8,0),CEILING(LEN(E25)*7/(J25-24),1)*16+20))
A26: D4 | B26: Z2 | D26: zone | E26: Internal Network | F26: 3 | G26: 1 | J26: =IF(H26<>"",H26,MIN(260,MAX(VLOOKUP(D26,Shape_Library!$A:$H,7,0),LEN(E26)*7+24))) | K26: =IF(I26<>"",I26,MAX(VLOOKUP(D26,Shape_Library!$A:$H,8,0),CEILING(LEN(E26)*7/(J26-24),1)*16+20))
A27: D4 | B27: N1 | C27: Z1 | D27: firewall | E27: Edge Firewall | F27: 1 | G27: 1 | J27: =IF(H27<>"",H27,MIN(260,MAX(VLOOKUP(D27,Shape_Library!$A:$H,7,0),LEN(E27)*7+24))) | K27: =IF(I27<>"",I27,MAX(VLOOKUP(D27,Shape_Library!$A:$H,8,0),CEILING(LEN(E27)*7/(J27-24),1)*16+20))
A28: D4 | B28: N2 | C28: Z1 | D28: load_balancer | E28: Load Balancer | F28: 1 | G28: 2 | J28: =IF(H28<>"",H28,MIN(260,MAX(VLOOKUP(D28,Shape_Library!$A:$H,7,0),LEN(E28)*7+24))) | K28: =IF(I28<>"",I28,MAX(VLOOKUP(D28,Shape_Library!$A:$H,8,0),CEILING(LEN(E28)*7/(J28-24),1)*16+20))
A29: D4 | B29: N3 | C29: Z2 | D29: server | E29: Web Server 01 | F29: 1 | G29: 1 | J29: =IF(H29<>"",H29,MIN(260,MAX(VLOOKUP(D29,Shape_Library!$A:$H,7,0),LEN(E29)*7+24))) | K29: =IF(I29<>"",I29,MAX(VLOOKUP(D29,Shape_Library!$A:$H,8,0),CEILING(LEN(E29)*7/(J29-24),1)*16+20))
A30: D4 | B30: N4 | C30: Z2 | D30: server | E30: Web Server 02 | F30: 1 | G30: 2 | J30: =IF(H30<>"",H30,MIN(260,MAX(VLOOKUP(D30,Shape_Library!$A:$H,7,0),LEN(E30)*7+24))) | K30: =IF(I30<>"",I30,MAX(VLOOKUP(D30,Shape_Library!$A:$H,8,0),CEILING(LEN(E30)*7/(J30-24),1)*16+20))
A31: D4 | B31: N5 | C31: Z2 | D31: database | E31: PostgreSQL Primary | F31: 2 | G31: 1 | J31: =IF(H31<>"",H31,MIN(260,MAX(VLOOKUP(D31,Shape_Library!$A:$H,7,0),LEN(E31)*7+24))) | K31: =IF(I31<>"",I31,MAX(VLOOKUP(D31,Shape_Library!$A:$H,8,0),CEILING(LEN(E31)*7/(J31-24),1)*16+20))
A32: D5 | B32: E1 | D32: entity | E32: CUSTOMER | F32: 1 | G32: 1 | J32: =IF(H32<>"",H32,MIN(260,MAX(VLOOKUP(D32,Shape_Library!$A:$H,7,0),LEN(E32)*7+24))) | K32: =IF(I32<>"",I32,MAX(VLOOKUP(D32,Shape_Library!$A:$H,8,0),CEILING(LEN(E32)*7/(J32-24),1)*16+20)) | M32: rows=id(PK);name;email;created_at
A33: D5 | B33: E2 | D33: entity | E33: ORDER | F33: 1 | G33: 2 | J33: =IF(H33<>"",H33,MIN(260,MAX(VLOOKUP(D33,Shape_Library!$A:$H,7,0),LEN(E33)*7+24))) | K33: =IF(I33<>"",I33,MAX(VLOOKUP(D33,Shape_Library!$A:$H,8,0),CEILING(LEN(E33)*7/(J33-24),1)*16+20)) | M33: rows=id(PK);customer_id(FK);status;total
A34: D5 | B34: E3 | D34: entity | E34: ORDER_ITEM | F34: 2 | G34: 2 | J34: =IF(H34<>"",H34,MIN(260,MAX(VLOOKUP(D34,Shape_Library!$A:$H,7,0),LEN(E34)*7+24))) | K34: =IF(I34<>"",I34,MAX(VLOOKUP(D34,Shape_Library!$A:$H,8,0),CEILING(LEN(E34)*7/(J34-24),1)*16+20)) | M34: rows=id(PK);order_id(FK);product_id(FK);qty
A35: D5 | B35: E4 | D35: entity | E35: PRODUCT | F35: 2 | G35: 1 | J35: =IF(H35<>"",H35,MIN(260,MAX(VLOOKUP(D35,Shape_Library!$A:$H,7,0),LEN(E35)*7+24))) | K35: =IF(I35<>"",I35,MAX(VLOOKUP(D35,Shape_Library!$A:$H,8,0),CEILING(LEN(E35)*7/(J35-24),1)*16+20)) | M35: rows=id(PK);sku;name;price

Sheet Edges
A1: diagram_id | B1: edge_id | C1: source_id | D1: target_id | E1: relation_type | F1: label | G1: waypoint_hint | H1: notes
A2: D1 | B2: e1 | C2: A1 | D2: B1 | E2: serving | H2: App serves business process
A3: D1 | B3: e2 | C3: A3 | D3: B1 | E3: serving
A4: D1 | B4: e3 | C4: A1 | D4: A3 | E4: realization | H4: Component realizes service
A5: D1 | B5: e4 | C5: A2 | D5: B2 | E5: serving
A6: D1 | B6: e5 | C6: T1 | D6: A1 | E6: assignment | H6: Cluster hosts platform
A7: D1 | B7: e6 | C7: T2 | D7: A2 | E7: assignment
A8: D2 | B8: e7 | C8: F1 | D8: F2 | E8: sequence_flow
A9: D2 | B9: e8 | C9: F2 | D9: F3 | E9: sequence_flow
A10: D2 | B10: e9 | C10: F3 | D10: F4 | E10: sequence_flow | F10: Yes | H10: Approved branch
A11: D2 | B11: e10 | C11: F3 | D11: F5 | E11: sequence_flow | F11: No | G11: route:right | H11: Rejected branch
A12: D2 | B12: e11 | C12: F4 | D12: F6 | E12: sequence_flow
A13: D2 | B13: e12 | C13: F6 | D13: F7 | E13: sequence_flow
A14: D2 | B14: e13 | C14: F5 | D14: F7 | E14: sequence_flow | G14: route:right | H14: Merge to end
A15: D3 | B15: e14 | C15: P2 | D15: P1 | E15: reports_to
A16: D3 | B16: e15 | C16: P3 | D16: P1 | E16: reports_to
A17: D3 | B17: e16 | C17: P4 | D17: P2 | E17: reports_to
A18: D3 | B18: e17 | C18: P5 | D18: P3 | E18: reports_to
A19: D3 | B19: e18 | C19: P4 | D19: P3 | E19: dotted_reporting | F19: project lead | H19: Matrix line
A20: D4 | B20: e19 | C20: N0 | D20: N1 | E20: physical_link | F20: WAN
A21: D4 | B21: e20 | C21: N1 | D21: N2 | E21: physical_link
A22: D4 | B22: e21 | C22: N2 | D22: N3 | E22: physical_link | F22: HTTP:80
A23: D4 | B23: e22 | C23: N2 | D23: N4 | E23: physical_link | F23: HTTP:80 | H23: Parallel edge → 8px offset (SZ-12)
A24: D4 | B24: e23 | C24: N3 | D24: N5 | E24: logical_link | F24: SQL
A25: D4 | B25: e24 | C25: N4 | D25: N5 | E25: logical_link | F25: SQL
A26: D5 | B26: e25 | C26: E1 | D26: E2 | E26: one_to_many | F26: 1 : N | H26: Customer places orders
A27: D5 | B27: e26 | C27: E2 | D27: E3 | E27: one_to_many | F27: 1 : N
A28: D5 | B28: e27 | C28: E4 | D28: E3 | E28: one_to_many | F28: 1 : N
